crudcrud/__init__.py
crudcrud/crud.py
crudcrud/crud_router.py
crudcrud/exceptions.py
crudcrud-0.1.1.dist-info/LICENSE.md
crudcrud-0.1.1.dist-info/METADATA
crudcrud-0.1.1.dist-info/WHEEL
crudcrud-0.1.1.dist-info/RECORD
