Metadata-Version: 2.1
Name: crudcrud
Version: 0.1.1
Summary: A simple CRUD library built with FastAPI and SQLModel.
Home-page: https://github.com/simbolico/crudcrud
License: MIT
Keywords: fastapi,sqlmodel,crud,api,database
Author: Kevin Saltarelli
Author-email: kevinqz@gmail.com
Requires-Python: >=3.10.0,<3.12
Classifier: Development Status :: 3 - Alpha
Classifier: Intended Audience :: Developers
Classifier: License :: OSI Approved :: MIT License
Classifier: Programming Language :: Python :: 3
Classifier: Programming Language :: Python :: 3.10
Classifier: Programming Language :: Python :: 3.11
Classifier: Topic :: Software Development :: Libraries :: Python Modules
Requires-Dist: fastapi (>=0.112.0,<0.113.0)
Requires-Dist: pydantic (>=2.10.6,<3.0.0)
Requires-Dist: sqlalchemy (>=2.0.38,<3.0.0)
Requires-Dist: sqlmodel (>=0.0.22,<0.0.23)
Requires-Dist: uvicorn[standard] (>=0.23.2,<0.24.0)
Project-URL: Repository, https://github.com/simbolico/crudcrud
